{
    "objectID": "53170b67bd8c738cb1b5279d238df47a",
    "created_at": "2024-12-21T11:22:21.105897+00:00",
    "ref": "castle-ward-walking-and-cycle-route",
    "title": "Castle Ward Walk Route",
    "headline_image_url": "https://upload.wikimedia.org/wikipedia/commons/thumb/7/7f/Castle_Ward_2.JPG/512px-Castle_Ward_2.JPG?20140914105855",
    "nearby": [
        {
            "description": "Strangford Lough",
            "objectID": "9e3785da7867329ca9270cbe54b8706a",
            "ref": "strangford-lough-cycle-route"
        },
        {
            "description": "Ards Peninsula Walk",
            "objectID": "6e63f45f27491a95d64e23012e3644af",
            "ref": "ards-peninsula-walking-route"
        }
    ],
    "gpx_url": "http://gps-routes.co.uk/A55CD9/home.nsf/All/CCB4E778652447798025802B0062E383/$FILE/Castle Ward.gpx",
    "_geoloc": {
        "lat": 54.3726044177,
        "lng": -5.5793423071
    },
    "images": [
        {
            "src": "https://upload.wikimedia.org/wikipedia/commons/thumb/7/7f/Castle_Ward_2.JPG/512px-Castle_Ward_2.JPG?20140914105855",
            "title": "Irishdeltaforce, CC BY-SA 3.0 <https://creativecommons.org/licenses/by-sa/3.0>, via Wikimedia Commons",
            "caption": "Castle Ward has been the home of the Ward family since ca. 1570. South-west facade shown here."
        },
        {
            "src": "https://upload.wikimedia.org/wikipedia/commons/thumb/9/94/Strangford_Lough_%2803%29%2C_August_2009.JPG/512px-Strangford_Lough_%2803%29%2C_August_2009.JPG?20090825195522",
            "title": "Ardfern, CC BY-SA 3.0 <https://creativecommons.org/licenses/by-sa/3.0>, via Wikimedia Commons",
            "caption": "Strangford Lough and Pier at Castle Ward, Strangford, County Down."
        },
        {
            "src": "https://upload.wikimedia.org/wikipedia/commons/thumb/2/25/View_south_along_the_Hoof_Trail_at_Castleward_-_geograph.org.uk_-_3545610.jpg/512px-View_south_along_the_Hoof_Trail_at_Castleward_-_geograph.org.uk_-_3545610.jpg?20220525213920",
            "title": "View south along the Hoof Trail at Castleward by Eric Jones, CC BY-SA 2.0 <https://creativecommons.org/licenses/by-sa/2.0>, via Wikimedia Commons",
            "caption": "View south along the Hoof Trail at Castleward"
        },
        {
            "src": "https://upload.wikimedia.org/wikipedia/commons/thumb/9/9f/Parkland_immediately_west_of_Castleward_House_-_geograph.org.uk_-_4613416.jpg/512px-Parkland_immediately_west_of_Castleward_House_-_geograph.org.uk_-_4613416.jpg?20230409063610",
            "title": "Parkland immediately west of Castleward House by Eric Jones, CC BY-SA 2.0 <https://creativecommons.org/licenses/by-sa/2.0>, via Wikimedia Commons",
            "caption": "Parkland immediately west of Castleward House"
        }
    ],
    "distance_km": 4.0,
    "description": "The Castle Ward estate covers 332 hectares (820 acres) with an 18th-century mansion, landscaped gardens and miles of great cycling and walking trails. The estate overlooks the beautiful Strangford Lough and includes the brilliant Lough Trail walking and cycle route. The National Trust have devised six great trails which expose you to the wonderful scenery around the estate. Features include the woodland trails in Castle Ward Forest, a waterside path along Temple Water and the lovely Walled Garden. You can virtually explore the Castle Ward estate using the google street view link below! To extend your cycling you can pick up the Strangford Lough circuit which takes you around the magnificent body of water.",
    "video_url": "https://www.youtube.com/embed/tl_SVBg9R8U?si=o-pL3uY1yLlgu04k"
}
