{
  "created_at": "2025-01-06T02:11:46.206238+00:00",
  "objectID": "78956b3cfa21f626c540fd93bec83413",
  "ref": "viking-way-walking-route",
  "title": "Viking Way Walking Route",
  "headline_image_url": "https://upload.wikimedia.org/wikipedia/commons/6/6c/Viking_Way_-_geograph.org.uk_-_618345.jpg",
  "nearby": [
    {
      "description": "Rutland Water",
      "objectID": "1c2f74e94b86c62210d62ff867df82d7",
      "ref": "rutland-water-walking-and-cycle-route"
    },
    {
      "description": "Grantham Canal",
      "objectID": "2d87caf5b0bd65ab4baa4bd0c91e88f1",
      "ref": "grantham-canal-walking-route"
    },
    {
      "description": "Woolsthorpe by Belvoir and Belvoir Castle",
      "objectID": "7e60efd9f5448855e00ffe751d365217",
      "ref": "woolsthorpe-by-belvoir-and-belvoir-castle-walking-route"
    },
    {
      "description": "Woodhall Spa",
      "objectID": "a57330331a68f84a3402a443b227dd80",
      "ref": "woodhall-spa-walking-route"
    },
    {
      "description": "Caistor",
      "objectID": "4c056e47fdfdd0d3b783d5bf81027e38",
      "ref": "caistor-walking-route"
    },
    {
      "description": "Viking Way Circular Walk",
      "objectID": "46c5fb4dabf2c3c844cdd61e06c9b612",
      "ref": "viking-way-circular-walk-walking-route"
    },
    {
      "description": "Water Rail Way",
      "objectID": "c823e3ef90c155a1056422b18ecf16e5",
      "ref": "water-rail-way-walking-and-cycle-route"
    },
    {
      "description": "Tealby",
      "objectID": "839c382ece9a7b574d3c1bce8eafc93b",
      "ref": "tealby-walking-route"
    },
    {
      "description": "Donington on Bain",
      "objectID": "900be18bef92a3391368f0a1d4200037",
      "ref": "donington-on-bain-walking-route"
    },
    {
      "description": "Belchford",
      "objectID": "95fcd911637fe3a63b65dbdf6a95bafb",
      "ref": "belchford-walking-route"
    },
    {
      "description": "Barton Upon Humber",
      "objectID": "21d929c152409fc5d09e17c97d2f6f8c",
      "ref": "barton-upon-humber-walking-route"
    },
    {
      "description": "Exton",
      "objectID": "21be9ceae72cec7449000760d136c67e",
      "ref": "exton-walking-route"
    },
    {
      "description": "Biscathorpe",
      "objectID": "9e1a4d44227cda21e6f95d55062902d9",
      "ref": "biscathorpe-walking-route"
    },
    {
      "description": "Spa Trail",
      "objectID": "ebd737c735832794855eaec0db8515a1",
      "ref": "spa-trail-walking-and-cycle-route"
    }
  ],
  "gpx_url": "https://raw.githubusercontent.com/rm-hull/gps-routes-api/refs/heads/main/data/routes/7/78956b3cfa21f626c540fd93bec83413.gpx",
  "_geoloc": {
    "lat": 53.6928912815,
    "lng": -0.4435760564
  },
  "images": [
    {
      "src": "https://upload.wikimedia.org/wikipedia/commons/6/6c/Viking_Way_-_geograph.org.uk_-_618345.jpg",
      "title": "Richard Croft / Viking Way",
      "caption": "Viking Way. Looking north towards Belmont near Donington-on-Bain"
    },
    {
      "src": "https://upload.wikimedia.org/wikipedia/commons/9/94/Viking_Way_-_geograph.org.uk_-_643217.jpg",
      "title": "Richard Croft / Viking Way",
      "caption": "The Viking Way on the cliff edge near Wellingore"
    },
    {
      "src": "https://upload.wikimedia.org/wikipedia/commons/4/4f/On_the_Viking_way_-_geograph.org.uk_-_1653153.jpg",
      "title": "steven ruffles / On the Viking way",
      "caption": "The path to Walesby church"
    },
    {
      "src": "https://upload.wikimedia.org/wikipedia/commons/d/d3/The_Viking_Way_-_geograph.org.uk_-_255277.jpg",
      "title": "Kate Jewell / The Viking Way",
      "caption": "The long distance footpath crosses the River Witham at this point."
    },
    {
      "src": "https://upload.wikimedia.org/wikipedia/commons/e/eb/Viking_Way_approaching_the_Weston_monument_at_Somerby_-_geograph.org.uk_-_851120.jpg",
      "title": "Tim Heaton / Viking Way approaching the Weston monument at Somerby",
      "caption": "The trail approaching the Weston monument at Somerby. A plaque states that the monument was erected by Edward and Ann Weston of Somerby Hall in 1770 to celebrate 29 years of marriage, and as a token of their gratitude to God for \"our life of peaceful leisure\"."
    },
    {
      "src": "https://upload.wikimedia.org/wikipedia/commons/5/5f/Viking_Way_and_Sambre_Beck_-_geograph.org.uk_-_242580.jpg",
      "title": "Richard Croft / Viking Way & Sambre Beck",
      "caption": "Sambre Beck. On the trail where the footpath to Grange Farm follows Sambre Beck near the northern end of Foxhall Wood"
    },
    {
      "src": "https://upload.wikimedia.org/wikipedia/commons/7/78/Nature_Magnified_-_geograph.org.uk_-_2617265.jpg",
      "title": "Nature Magnified by Richard Croft, CC BY-SA 2.0 <https://creativecommons.org/licenses/by-sa/2.0>, via Wikimedia Commons",
      "caption": "Nature Magnified. Sculptures on the Spa Trail running between Woodhall Spa and Horncastle. This section is also suitable for cyclists."
    },
    {
      "src": "https://upload.wikimedia.org/wikipedia/commons/d/d1/Scamblesby_Grove_-_geograph.org.uk_-_43866.jpg",
      "title": "Tony Atkin / Scamblesby Grove",
      "caption": "Scamblesby Grove. This farmhouse lies at the foot of the chalk escarpment. At this point the escarpment is wooded. The photograph was taken from the adjoining grid square to the west on the Viking Way footpath."
    }
  ],
  "distance_km": 237.0,
  "description": "Follow in the footsteps of the Norse invaders on this long distance walk from the Humber Bridge to Oakham in Rutland. The walk passes through the Lincolnshire Wolds AONB and some delightful Leicestershire countryside before rounding Rutland water to the finish point at Oakham. Walk highlights include",
  "details": [
    {
      "subtitle": "Pubs/Cafes",
      "content": "At the start of the route at Barton Upon Humber there's The Viking Way Cafe Bar. The cafe is housed in a historic lifeboat station on the Humber Estuary next to the bridge. They serve a good range of meals and snacks and can be found at postcode DN18 5BD. The Harbour Cafe is in a lovely spot overlooking Whitwell Harbour on Rutland Water. It's a great place to stop on the route and rest your legs. The cafe is open 7 days a week from March until November then they open Friday, Saturday and Sunday through the Winter. They offer a wide variety of, cooked breakfasts, home cooked lunches, snacks, great coffee and cakes in a relaxed family friendly environment. There's a great outdoor seating area with fine views of the water. You can find the cafe on Bull Brigg Lane with a postcode of LE15 8BL for your sat navs. In the Lincolnshire Wolds be sure to pay a visit to the King's Head in the historic village of Tealby. Dating from 1367 the inn is notable as the oldest thatched pub in Lincolnshire. Inside there's a charming interior with a cosy lounge and a restaurant. Outside there's a lovely large garden area to relax in on warmer days. You can find them at 11 Kingsway with a postcode of LN8 3YA for your sat navs. The pub is also dog friendly. In the pretty village of Donington on Bain there's the Black Horse Inn. The 18th century inn serves high quality food and has a good selection of ales. They also have a nice garden area for warmer days. You can find them on the Main Road with postcode LN11 9TJ for your sat navs. The village is also worth exploring with a 12th century church and nice views of the River Bain to enjoy. The village of Belchford is on the route in the Lincolnshire Wolds AONB. Here you'll find the Bluebell Inn, a traditional pub serving high quality dishes. They also have a garden area to enjoy. You can find them on the Main Road at postcode LN9 6LQ for your sat navs. Also in the village is an 18th century church with a 15th century font. Near Rutland Water you'll pass through the delightful village of Exton where you'll find the Fox and Hounds. The attractive 17th century coaching inn overlooks the village green in the village. There's a cosy interior with a real log fire and a stunning English country garden for warmer weather. You can find them at postcode LE15 8AP for your sat navs. Just to the east you can also explore the parkland of the old Exton Hall and visit the pretty Fort Henry Lakes."
    },
    {
      "subtitle": "Further Information and Other Local Ideas",
      "content": "For extra walking around the trail you could try the Viking Way Circular Walk at Woodhall Spa. This route uses a section of the Viking Way and the Water Rail Way to create a circular walk around the Lincolnshire Wolds town. It takes you through the countryside before a nice waterside section along the River Witham. For more walking ideas in the area see the Lincolnshire Walks page."
    }
  ],
  "district": "Barton-upon-Humber",
  "county": "North Lincolnshire",
  "region": null,
  "country": "United Kingdom",
  "gazetteer_found": true,
  "nominatim_found": true,
  "display_address": "The Sloop, 81, Waterside Road, Barton Waterside, Barton-upon-Humber, North Lincolnshire, England, DN18 5BA, United Kingdom",
  "postcode": "DN18 5BA",
  "state": "England",
  "llama_cpp": true,
  "estimated_duration": "2 days",
  "difficulty": "moderate",
  "terrain": [
    "woodland",
    "rural"
  ],
  "points_of_interest": [
    "historical sites",
    "countryside"
  ],
  "facilities": [
    "car park"
  ],
  "route_type": "out and back",
  "activities": [
    "walking"
  ]
}