{
  "objectID": "4fbf2e224e2869fc6253c09eba4b3e1b",
  "created_at": "2024-12-18T04:16:44.187441+00:00",
  "ref": "kinghorn-loch-walking-route",
  "title": "Kinghorn Loch Walking Route",
  "headline_image_url": "https://upload.wikimedia.org/wikipedia/commons/b/b8/Kinghorn_Loch_-_geograph.org.uk_-_75069.jpg",
  "nearby": [
    {
      "description": "Aberdour to Burntisland Coastal Path",
      "objectID": "161722a62859580475ac24cac5ce3fd5",
      "ref": "aberdour-to-burntisland-coastal-path-walking-route"
    },
    {
      "description": "Fife Coastal Path",
      "objectID": "636c198ff6841e6415f206ca7cfb9ab8",
      "ref": "fife-coastal-path-walking-route"
    },
    {
      "description": "Elie to Pittenweem Walk",
      "objectID": "2c61c13e7e1e300ad9fd6fc65709f354",
      "ref": "elie-to-pittenweem-walk-walking-route"
    },
    {
      "description": "Loch Fitty",
      "objectID": "ef283a5e9475e75edfead0500a9c6331",
      "ref": "loch-fitty-walking-route"
    },
    {
      "description": "Townhill Country Park",
      "objectID": "f66d7b2a8e36497ca8c976d9d60ee77e",
      "ref": "townhill-country-park-walking-and-cycle-route"
    },
    {
      "description": "Dalgety Bay to Aberdour Coastal Path",
      "objectID": "6961775014737669010476605d409271",
      "ref": "dalgety-bay-to-aberdour-coastal-path-walking-route"
    },
    {
      "description": "Lower Largo to Shell Bay and Elie Coastal Walk",
      "objectID": "65769e80f0decd99940723a76f2239da",
      "ref": "lower-largo-to-shell-bay-and-elie-coastal-walk-walking-route"
    },
    {
      "description": "Leven to Lower Largo",
      "objectID": "79e205c8fc78fce308028ccb9f3347f9",
      "ref": "leven-to-lower-largo-walking-route"
    },
    {
      "description": "Elie and Earlsferry Chain Walk",
      "objectID": "1e7deba0adf88e693257adb035e97934",
      "ref": "elie-and-earlsferry-chain-walk"
    }
  ],
  "gpx_url": "http://gps-routes.co.uk/A55CD9/home.nsf/All/E1D6A395A8FB6C1886258702005B6671/$FILE/Kinghorn Loch.gpx",
  "_geoloc": {
    "lat": 56.0747221354,
    "lng": -3.1909416532
  },
  "images": [
    {
      "src": "https://upload.wikimedia.org/wikipedia/commons/b/b8/Kinghorn_Loch_-_geograph.org.uk_-_75069.jpg",
      "title": "John Darcy\u00a0/\u00a0Kinghorn Loch",
      "caption": "Kinghorn Loch. Craigencalt Farm Ecology Centre and Community Woodland, and the closely associated boat launching area is a very popular location for anglers"
    },
    {
      "src": "https://upload.wikimedia.org/wikipedia/commons/7/7e/Craigencalt_Ecology_Centre_-_geograph.org.uk_-_666836.jpg",
      "title": "Paul McIlroy\u00a0/\u00a0Craigencalt Ecology Centre",
      "caption": "Craigencalt Ecology Centre. Situated on north shore of Kinghorn Loch this environmental education centre offers practical demonstrations and examples of alternative forms of energy, recycling etc"
    },
    {
      "src": "https://upload.wikimedia.org/wikipedia/commons/9/9e/Three_stoojes_-_geograph.org.uk_-_879860.jpg",
      "title": "Robin Clark\u00a0/\u00a0Three stoojes",
      "caption": "Three stoojes. The loch which is part of a project which that is self efficient. There is much to see at the park and hope they keep up the great work."
    },
    {
      "src": "https://upload.wikimedia.org/wikipedia/commons/a/af/K14_Loch_from_hide.jpg",
      "title": "Cemitchell at English Wikipedia, CC BY 3.0 <https://creativecommons.org/licenses/by/3.0>, via Wikimedia Commons",
      "caption": "Loch from the bird hide"
    }
  ],
  "distance_km": 1.0,
  "description": "This pretty little loch is located just inland of the coastal settlements of Kinghorn and Burntisland in Fife. At the site there's some nice waterside and woodland trails plus a bird hide where you can look out for a variety of water loving birds. At the northern side of the water there's the Earthship Fife Visitor Centre where you can enjoy a bite to eat at the cafe.",
  "video_url": "https://www.youtube.com/embed/hDMoPBebEIw",
  "postcode": "KY3 9YG",
  "county": "Fife",
  "region": "Scotland",
  "country": "Scotland"
}