{
  "created_at": "2025-01-06T05:07:08.752604+00:00",
  "objectID": "0ee8e8143856fd9ce9c8286e5ac3ebbd",
  "ref": "offas-dyke-path-walking-route",
  "title": "Offa's Dyke Path National Trail Walking Route",
  "headline_image_url": "https://upload.wikimedia.org/wikipedia/commons/2/2d/Offa%27s_Dyke_Path_-_geograph.org.uk_-_392604.jpg",
  "nearby": [
    {
      "description": "Tintern Abbey",
      "objectID": "cf211bde830017fdc4432815b9591546",
      "ref": "tintern-abbey-walking-route"
    },
    {
      "description": "Devil's Pulpit",
      "objectID": "6d9697a194a2e457625aa12ddb16197f",
      "ref": "devils-pulpit-walking-route"
    },
    {
      "description": "Hergest Ridge",
      "objectID": "cc0fc19f260d5cd701eff3508c0f9f29",
      "ref": "hergest-ridge-walking-route"
    },
    {
      "description": "Hay Bluff",
      "objectID": "7dfb501453683692bb597af001e9f2d4",
      "ref": "hay-bluff-walking-route"
    },
    {
      "description": "World's End Llangollen",
      "objectID": "9ad997f6a414c7e3282d750670c75b11",
      "ref": "worlds-end-llangollen-walking-route"
    },
    {
      "description": "Moel Famau Country Park",
      "objectID": "bcb4017ef572ed66f547225b372cc519",
      "ref": "moel-famau-country-park-walking-route"
    },
    {
      "description": "Ty Mawr Country Park",
      "objectID": "613de637f8d488812010d0b74f33ecea",
      "ref": "ty-mawr-country-park-walking-route"
    },
    {
      "description": "Llandegla Forest",
      "objectID": "c1b533310a080508179332e535a352cd",
      "ref": "llandegla-forest-walking-and-cycle-route"
    },
    {
      "description": "Pontcysyllte Aqueduct",
      "objectID": "6817e9c8aa2f705335996399af3c8220",
      "ref": "pontcysyllte-aqueduct-walking-route"
    },
    {
      "description": "Moel Arthur",
      "objectID": "df9dd114ef775705d39ef186fb1849da",
      "ref": "moel-arthur-walking-route"
    },
    {
      "description": "Kington",
      "objectID": "81980bfb64aabe86f6f3fa3f725e3a88",
      "ref": "kington-walking-route"
    },
    {
      "description": "Cats Back",
      "objectID": "7b5500106ec042d5beb4507b915c2504",
      "ref": "cats-back-walking-route"
    },
    {
      "description": "Penycloddiau",
      "objectID": "6cd8c833fbb10b08b3290fe81fe8f3d1",
      "ref": "penycloddiau-walking-route"
    }
  ],
  "gpx_url": "https://raw.githubusercontent.com/rm-hull/gps-routes-api/refs/heads/main/data/routes/0/0ee8e8143856fd9ce9c8286e5ac3ebbd.gpx",
  "_geoloc": {
    "lat": 51.6326106486,
    "lng": -2.6483841664
  },
  "images": [
    {
      "src": "https://upload.wikimedia.org/wikipedia/commons/2/2d/Offa%27s_Dyke_Path_-_geograph.org.uk_-_392604.jpg",
      "title": "George Evans [CC BY-SA 2.0 (http://creativecommons.org/licenses/by-sa/2.0)], via Wikimedia Commons",
      "caption": "A barren, stony area, where the cairns mark the Offa's Dyke Path and the England-Wales border, along a wide ridge between the Olchon Valley and Vale of Ewyas."
    },
    {
      "src": "https://upload.wikimedia.org/wikipedia/commons/thumb/a/a7/Offa%27s_Dyke_Path_marker_stone.jpg/256px-Offa%27s_Dyke_Path_marker_stone.jpg",
      "title": "By Andy Dingley (Own work) [CC BY-SA 3.0 (http://creativecommons.org/licenses/by-sa/3.0)], via Wikimedia Commons",
      "caption": "Marker stone at Chepstow"
    },
    {
      "src": "https://upload.wikimedia.org/wikipedia/commons/7/77/Offa%27s_Dyke_Path_-_geograph.org.uk_-_205226.jpg",
      "title": "Eirian Evans [CC BY-SA 2.0 (http://creativecommons.org/licenses/by-sa/2.0)], via Wikimedia Commons",
      "caption": "Looking south down a broad section of the Offa's Dyke path. Here the path passes around the western side of Moel Gyw."
    },
    {
      "src": "https://upload.wikimedia.org/wikipedia/commons/thumb/5/54/Offa%27s_Dyke_Path._-_geograph.org.uk_-_760299.jpg/256px-Offa%27s_Dyke_Path._-_geograph.org.uk_-_760299.jpg",
      "title": "David Quinn [CC BY-SA 2.0 (http://creativecommons.org/licenses/by-sa/2.0)], via Wikimedia Commons",
      "caption": "The path where it crosses the old road between Cilcain and Llangynhafal. It is 1 and a half miles to Moel Famau from here."
    },
    {
      "src": "https://upload.wikimedia.org/wikipedia/commons/e/ea/Offa%27s_Dyke_path_-_geograph.org.uk_-_1465159.jpg",
      "title": "AntJB / Offa's Dyke path",
      "caption": "Heading up Moel Fammau"
    },
    {
      "src": "https://upload.wikimedia.org/wikipedia/commons/3/39/Offa%27s_Dyke_Path_-_geograph.org.uk_-_205230.jpg",
      "title": "Eirian Evans / Offa's Dyke Path",
      "caption": "The path crosses the field - you can see it as a darker green in the field ahead. When it reaches the trees, it bears right around the western side of Moel Gyw."
    },
    {
      "src": "https://upload.wikimedia.org/wikipedia/commons/0/0e/Penycloddiau_-_geograph.org.uk_-_43229.jpg",
      "title": "Philip Halling / Penycloddiau",
      "caption": "Penycloddiau. View north on Offa's Dyke Path from Penycloddiau fort on the Clwydian Hills."
    },
    {
      "src": "https://upload.wikimedia.org/wikipedia/commons/c/c9/Moelydd_-_geograph.org.uk_-_343018.jpg",
      "title": "Philip Halling / Moelydd",
      "caption": "Moelydd. View to the south from the summit of Moelydd. The path crosses this hill which provides good views all round. This is a view to the south across the Severn basin."
    }
  ],
  "distance_km": 285.0,
  "description": "This incredible 177 mile trail starts on the River Severn Estuary in Gloucestershire in England before taking you over the border into Wales and on through some truly splendid mountainous scenery. Highlights on the route include the gorgeous Wye Valley AONB, crossing from England into Wales along the splendid Hergest Ridge and the awe inspiring Brecon Beacons National Park. You'll also pass the popular Moel Famau and Moel Arthur in the stunning Clwydian Range. For more information on this trail please visit the National Trail web site",
  "details": [
    {
      "subtitle": "Pubs/Cafes",
      "content": "On the route you will pass the pretty village of Bodfari near Moel Arthur in the Clwydian Hills. In the village you will find The Dinorben Arms, a traditional pub steeped in history. It has an attractive interior, a great menu and good selection of drinks. There's also a fabulous outdoor terrace where you can relax outside and soak in the views of the surrounding hills and countryside. You can find the pub at postcode LL16 4DA for your sat navs. It's worth exploring the pretty village too where you can visit the Church of St Stephen, which lies at the heart of the settlement, and has its origins in medieval times, dating back to at least the eleventh century. In Powys based Knighton there's the noteworthy Horse and Jockey to consider. The traditional 14th century coaching inn includes a cosy interior with original beams and open fires. There's a nice garden area for warmer weather and a fine restaurant which serves good quality dishes. You can find them at Wylcwm Place, Station Rd, LD7 1AE. You could also head to the Knighton Hotel for high quality accommodation. You can find them at Broad Street with postcode LD7 1BL for your sat navs. Just to the west you'll find the Ponderosa Cafe on the Horseshoe Pass. The large cafe serves a good range of meals and snacks. There's a splendid outdoor seating area with excellent views over the surrounding hills. At 1,400 ft above sea level you can see the Clwydian Mountain range and on a very clear day the three peaks of Snowdon. There's also Bed & Breakfast Accommodation and a large car park here. Just to the west of the scenic World's End in Llangollen you'll find the Ponderosa Cafe on the 'Horseshoe Pass'. The large cafe serves a good range of meals and snacks. There's a splendid outdoor seating area with excellent views over the surrounding hills. At 1,400 ft above sea level you can see the Clwydian Mountain range and on a very clear day the three peaks of Snowdon. There's also Bed & Breakfast Accommodation, a gift shop and a large car park at the extensive complex. Postcode is LL20 8DR."
    },
    {
      "subtitle": "Further Information and Other Local Ideas",
      "content": "In the Black Mountains near Hay Bluff you could take a small detour from the route to pick up the circular Cat's Back Walk. The wonderful knife edge ridge walk is a popular local climb and considered to be Herefordshire's own Striding Edge. The route provides great views into England on one side, and Wales on the other. There's a handy car park just south of the ridge or you could start from the pretty little village of Michaelchurch Escley where there's a nice riverside pub to visit."
    }
  ],
  "video_url": "https://www.youtube.com/embed/L372wIAefBY",
  "county": "Gloucestershire",
  "region": "South West",
  "country": "England",
  "gazetteer_found": true
}